LICENSE
README.md
setup.py
sealea/__init__.py
sealea/config.py
sealea/exceptions.py
sealea/extractors.py
sealea/story.py
sealea/types.py
sealea/utils.py
sealea/zones.py
sealea.egg-info/PKG-INFO
sealea.egg-info/SOURCES.txt
sealea.egg-info/dependency_links.txt
sealea.egg-info/requires.txt
sealea.egg-info/top_level.txt
sealea/mixins/__init__.py
sealea/mixins/account.py
sealea/mixins/album.py
sealea/mixins/auth.py
sealea/mixins/bloks.py
sealea/mixins/challenge.py
sealea/mixins/clip.py
sealea/mixins/collection.py
sealea/mixins/comment.py
sealea/mixins/direct.py
sealea/mixins/fbsearch.py
sealea/mixins/fundraiser.py
sealea/mixins/hashtag.py
sealea/mixins/highlight.py
sealea/mixins/igtv.py
sealea/mixins/insights.py
sealea/mixins/location.py
sealea/mixins/media.py
sealea/mixins/multiple_accounts.py
sealea/mixins/notification.py
sealea/mixins/password.py
sealea/mixins/photo.py
sealea/mixins/private.py
sealea/mixins/public.py
sealea/mixins/share.py
sealea/mixins/story.py
sealea/mixins/timeline.py
sealea/mixins/totp.py
sealea/mixins/track.py
sealea/mixins/user.py
sealea/mixins/video.py